rest_typed_models/README.md
rest_typed_models/__init__.py
rest_typed_models/__version__.py
rest_typed_models/serializers.py
django_rest_typed_models-0.1.0.dist-info/LICENSE
django_rest_typed_models-0.1.0.dist-info/WHEEL
django_rest_typed_models-0.1.0.dist-info/METADATA
django_rest_typed_models-0.1.0.dist-info/RECORD
