Metadata-Version: 2.1
Name: django-rest-typed-models
Version: 0.1.0
Summary: Typed model serializers for Django REST Framework.
License: MIT
Author: Krystof Beuermann
Author-email: krystof+django@blackbox.ms
Requires-Python: >=3.10,<4.0
Classifier: License :: OSI Approved :: MIT License
Classifier: Programming Language :: Python :: 3
Classifier: Programming Language :: Python :: 3.10
Classifier: Programming Language :: Python :: 3.11
